{"remainingRequest":"/Users/macsen/Desktop/Macsen/rltx-webpack/node_modules/_babel-loader@6.2.10@babel-loader/lib/index.js??ref--2-1!/Users/macsen/Desktop/Macsen/rltx-webpack/api/ticketDetailService.js","dependencies":[{"path":"/Users/macsen/Desktop/Macsen/rltx-webpack/api/ticketDetailService.js","mtime":1511527701000},{"path":"/Users/macsen/Desktop/Macsen/rltx-webpack/node_modules/_cache-loader@1.2.0@cache-loader/dist/cjs.js","mtime":1510929699000},{"path":"/Users/macsen/Desktop/Macsen/rltx-webpack/node_modules/_babel-loader@6.2.10@babel-loader/lib/index.js","mtime":1481808750000}],"contextDependencies":[],"result":["'use strict';\n\nObject.defineProperty(exports, \"__esModule\", {\n  value: true\n});\nexports.downloadTemplate = exports.downloadErrorData = exports.exportCsv = exports.get = exports.edit = exports.add = exports.deleted = exports.getSearch = exports.getColumn = exports.list = undefined;\n\nvar cov_ov9eokzlk = function () {\n  var path = '/Users/macsen/Desktop/Macsen/rltx-webpack/api/ticketDetailService.js',\n      hash = '9f9d6e5026078a5cd7601832a0a28da8b1265802',\n      global = new Function('return this')(),\n      gcv = '__coverage__',\n      coverageData = {\n    path: '/Users/macsen/Desktop/Macsen/rltx-webpack/api/ticketDetailService.js',\n    statementMap: {\n      '0': {\n        start: {\n          line: 7,\n          column: 18\n        },\n        end: {\n          line: 7,\n          column: 56\n        }\n      },\n      '1': {\n        start: {\n          line: 20,\n          column: 17\n        },\n        end: {\n          line: 20,\n          column: 58\n        }\n      },\n      '2': {\n        start: {\n          line: 21,\n          column: 2\n        },\n        end: {\n          line: 23,\n          column: 5\n        }\n      },\n      '3': {\n        start: {\n          line: 22,\n          column: 4\n        },\n        end: {\n          line: 22,\n          column: 24\n        }\n      },\n      '4': {\n        start: {\n          line: 31,\n          column: 17\n        },\n        end: {\n          line: 31,\n          column: 60\n        }\n      },\n      '5': {\n        start: {\n          line: 32,\n          column: 2\n        },\n        end: {\n          line: 34,\n          column: 5\n        }\n      },\n      '6': {\n        start: {\n          line: 33,\n          column: 4\n        },\n        end: {\n          line: 33,\n          column: 19\n        }\n      },\n      '7': {\n        start: {\n          line: 42,\n          column: 17\n        },\n        end: {\n          line: 42,\n          column: 62\n        }\n      },\n      '8': {\n        start: {\n          line: 43,\n          column: 2\n        },\n        end: {\n          line: 45,\n          column: 5\n        }\n      },\n      '9': {\n        start: {\n          line: 44,\n          column: 4\n        },\n        end: {\n          line: 44,\n          column: 19\n        }\n      },\n      '10': {\n        start: {\n          line: 55,\n          column: 17\n        },\n        end: {\n          line: 55,\n          column: 77\n        }\n      },\n      '11': {\n        start: {\n          line: 56,\n          column: 2\n        },\n        end: {\n          line: 58,\n          column: 5\n        }\n      },\n      '12': {\n        start: {\n          line: 57,\n          column: 4\n        },\n        end: {\n          line: 57,\n          column: 12\n        }\n      },\n      '13': {\n        start: {\n          line: 67,\n          column: 17\n        },\n        end: {\n          line: 67,\n          column: 57\n        }\n      },\n      '14': {\n        start: {\n          line: 68,\n          column: 2\n        },\n        end: {\n          line: 70,\n          column: 5\n        }\n      },\n      '15': {\n        start: {\n          line: 69,\n          column: 4\n        },\n        end: {\n          line: 69,\n          column: 19\n        }\n      },\n      '16': {\n        start: {\n          line: 79,\n          column: 17\n        },\n        end: {\n          line: 79,\n          column: 66\n        }\n      },\n      '17': {\n        start: {\n          line: 80,\n          column: 2\n        },\n        end: {\n          line: 82,\n          column: 5\n        }\n      },\n      '18': {\n        start: {\n          line: 81,\n          column: 4\n        },\n        end: {\n          line: 81,\n          column: 19\n        }\n      },\n      '19': {\n        start: {\n          line: 92,\n          column: 17\n        },\n        end: {\n          line: 92,\n          column: 74\n        }\n      },\n      '20': {\n        start: {\n          line: 93,\n          column: 2\n        },\n        end: {\n          line: 93,\n          column: 23\n        }\n      },\n      '21': {\n        start: {\n          line: 94,\n          column: 2\n        },\n        end: {\n          line: 96,\n          column: 5\n        }\n      },\n      '22': {\n        start: {\n          line: 95,\n          column: 4\n        },\n        end: {\n          line: 95,\n          column: 19\n        }\n      },\n      '23': {\n        start: {\n          line: 104,\n          column: 17\n        },\n        end: {\n          line: 104,\n          column: 45\n        }\n      },\n      '24': {\n        start: {\n          line: 105,\n          column: 2\n        },\n        end: {\n          line: 107,\n          column: 5\n        }\n      },\n      '25': {\n        start: {\n          line: 106,\n          column: 4\n        },\n        end: {\n          line: 106,\n          column: 29\n        }\n      },\n      '26': {\n        start: {\n          line: 114,\n          column: 17\n        },\n        end: {\n          line: 114,\n          column: 48\n        }\n      },\n      '27': {\n        start: {\n          line: 115,\n          column: 2\n        },\n        end: {\n          line: 117,\n          column: 5\n        }\n      },\n      '28': {\n        start: {\n          line: 116,\n          column: 4\n        },\n        end: {\n          line: 116,\n          column: 29\n        }\n      },\n      '29': {\n        start: {\n          line: 124,\n          column: 17\n        },\n        end: {\n          line: 124,\n          column: 56\n        }\n      },\n      '30': {\n        start: {\n          line: 125,\n          column: 2\n        },\n        end: {\n          line: 127,\n          column: 5\n        }\n      },\n      '31': {\n        start: {\n          line: 126,\n          column: 4\n        },\n        end: {\n          line: 126,\n          column: 29\n        }\n      }\n    },\n    fnMap: {\n      '0': {\n        name: 'list',\n        decl: {\n          start: {\n            line: 19,\n            column: 9\n          },\n          end: {\n            line: 19,\n            column: 13\n          }\n        },\n        loc: {\n          start: {\n            line: 19,\n            column: 28\n          },\n          end: {\n            line: 24,\n            column: 1\n          }\n        },\n        line: 19\n      },\n      '1': {\n        name: '(anonymous_1)',\n        decl: {\n          start: {\n            line: 21,\n            column: 29\n          },\n          end: {\n            line: 21,\n            column: 30\n          }\n        },\n        loc: {\n          start: {\n            line: 21,\n            column: 50\n          },\n          end: {\n            line: 23,\n            column: 3\n          }\n        },\n        line: 21\n      },\n      '2': {\n        name: 'getColumn',\n        decl: {\n          start: {\n            line: 30,\n            column: 9\n          },\n          end: {\n            line: 30,\n            column: 18\n          }\n        },\n        loc: {\n          start: {\n            line: 30,\n            column: 23\n          },\n          end: {\n            line: 35,\n            column: 1\n          }\n        },\n        line: 30\n      },\n      '3': {\n        name: '(anonymous_3)',\n        decl: {\n          start: {\n            line: 32,\n            column: 23\n          },\n          end: {\n            line: 32,\n            column: 24\n          }\n        },\n        loc: {\n          start: {\n            line: 32,\n            column: 39\n          },\n          end: {\n            line: 34,\n            column: 3\n          }\n        },\n        line: 32\n      },\n      '4': {\n        name: 'getSearch',\n        decl: {\n          start: {\n            line: 41,\n            column: 9\n          },\n          end: {\n            line: 41,\n            column: 18\n          }\n        },\n        loc: {\n          start: {\n            line: 41,\n            column: 23\n          },\n          end: {\n            line: 46,\n            column: 1\n          }\n        },\n        line: 41\n      },\n      '5': {\n        name: '(anonymous_5)',\n        decl: {\n          start: {\n            line: 43,\n            column: 23\n          },\n          end: {\n            line: 43,\n            column: 24\n          }\n        },\n        loc: {\n          start: {\n            line: 43,\n            column: 39\n          },\n          end: {\n            line: 45,\n            column: 3\n          }\n        },\n        line: 43\n      },\n      '6': {\n        name: 'deleted',\n        decl: {\n          start: {\n            line: 54,\n            column: 9\n          },\n          end: {\n            line: 54,\n            column: 16\n          }\n        },\n        loc: {\n          start: {\n            line: 54,\n            column: 31\n          },\n          end: {\n            line: 59,\n            column: 1\n          }\n        },\n        line: 54\n      },\n      '7': {\n        name: '(anonymous_7)',\n        decl: {\n          start: {\n            line: 56,\n            column: 30\n          },\n          end: {\n            line: 56,\n            column: 31\n          }\n        },\n        loc: {\n          start: {\n            line: 56,\n            column: 39\n          },\n          end: {\n            line: 58,\n            column: 3\n          }\n        },\n        line: 56\n      },\n      '8': {\n        name: 'add',\n        decl: {\n          start: {\n            line: 66,\n            column: 9\n          },\n          end: {\n            line: 66,\n            column: 12\n          }\n        },\n        loc: {\n          start: {\n            line: 66,\n            column: 27\n          },\n          end: {\n            line: 71,\n            column: 1\n          }\n        },\n        line: 66\n      },\n      '9': {\n        name: '(anonymous_9)',\n        decl: {\n          start: {\n            line: 68,\n            column: 30\n          },\n          end: {\n            line: 68,\n            column: 31\n          }\n        },\n        loc: {\n          start: {\n            line: 68,\n            column: 46\n          },\n          end: {\n            line: 70,\n            column: 3\n          }\n        },\n        line: 68\n      },\n      '10': {\n        name: 'edit',\n        decl: {\n          start: {\n            line: 78,\n            column: 9\n          },\n          end: {\n            line: 78,\n            column: 13\n          }\n        },\n        loc: {\n          start: {\n            line: 78,\n            column: 34\n          },\n          end: {\n            line: 83,\n            column: 1\n          }\n        },\n        line: 78\n      },\n      '11': {\n        name: '(anonymous_11)',\n        decl: {\n          start: {\n            line: 80,\n            column: 30\n          },\n          end: {\n            line: 80,\n            column: 31\n          }\n        },\n        loc: {\n          start: {\n            line: 80,\n            column: 46\n          },\n          end: {\n            line: 82,\n            column: 3\n          }\n        },\n        line: 80\n      },\n      '12': {\n        name: 'get',\n        decl: {\n          start: {\n            line: 91,\n            column: 9\n          },\n          end: {\n            line: 91,\n            column: 12\n          }\n        },\n        loc: {\n          start: {\n            line: 91,\n            column: 27\n          },\n          end: {\n            line: 97,\n            column: 1\n          }\n        },\n        line: 91\n      },\n      '13': {\n        name: '(anonymous_13)',\n        decl: {\n          start: {\n            line: 94,\n            column: 29\n          },\n          end: {\n            line: 94,\n            column: 30\n          }\n        },\n        loc: {\n          start: {\n            line: 94,\n            column: 45\n          },\n          end: {\n            line: 96,\n            column: 3\n          }\n        },\n        line: 94\n      },\n      '14': {\n        name: 'exportCsv',\n        decl: {\n          start: {\n            line: 103,\n            column: 9\n          },\n          end: {\n            line: 103,\n            column: 18\n          }\n        },\n        loc: {\n          start: {\n            line: 103,\n            column: 39\n          },\n          end: {\n            line: 108,\n            column: 1\n          }\n        },\n        line: 103\n      },\n      '15': {\n        name: '(anonymous_15)',\n        decl: {\n          start: {\n            line: 105,\n            column: 29\n          },\n          end: {\n            line: 105,\n            column: 30\n          }\n        },\n        loc: {\n          start: {\n            line: 105,\n            column: 49\n          },\n          end: {\n            line: 107,\n            column: 3\n          }\n        },\n        line: 105\n      },\n      '16': {\n        name: 'downloadErrorData',\n        decl: {\n          start: {\n            line: 113,\n            column: 9\n          },\n          end: {\n            line: 113,\n            column: 26\n          }\n        },\n        loc: {\n          start: {\n            line: 113,\n            column: 47\n          },\n          end: {\n            line: 118,\n            column: 1\n          }\n        },\n        line: 113\n      },\n      '17': {\n        name: '(anonymous_17)',\n        decl: {\n          start: {\n            line: 115,\n            column: 30\n          },\n          end: {\n            line: 115,\n            column: 31\n          }\n        },\n        loc: {\n          start: {\n            line: 115,\n            column: 50\n          },\n          end: {\n            line: 117,\n            column: 3\n          }\n        },\n        line: 115\n      },\n      '18': {\n        name: 'downloadTemplate',\n        decl: {\n          start: {\n            line: 123,\n            column: 9\n          },\n          end: {\n            line: 123,\n            column: 25\n          }\n        },\n        loc: {\n          start: {\n            line: 123,\n            column: 46\n          },\n          end: {\n            line: 128,\n            column: 1\n          }\n        },\n        line: 123\n      },\n      '19': {\n        name: '(anonymous_19)',\n        decl: {\n          start: {\n            line: 125,\n            column: 29\n          },\n          end: {\n            line: 125,\n            column: 30\n          }\n        },\n        loc: {\n          start: {\n            line: 125,\n            column: 49\n          },\n          end: {\n            line: 127,\n            column: 3\n          }\n        },\n        line: 125\n      }\n    },\n    branchMap: {},\n    s: {\n      '0': 0,\n      '1': 0,\n      '2': 0,\n      '3': 0,\n      '4': 0,\n      '5': 0,\n      '6': 0,\n      '7': 0,\n      '8': 0,\n      '9': 0,\n      '10': 0,\n      '11': 0,\n      '12': 0,\n      '13': 0,\n      '14': 0,\n      '15': 0,\n      '16': 0,\n      '17': 0,\n      '18': 0,\n      '19': 0,\n      '20': 0,\n      '21': 0,\n      '22': 0,\n      '23': 0,\n      '24': 0,\n      '25': 0,\n      '26': 0,\n      '27': 0,\n      '28': 0,\n      '29': 0,\n      '30': 0,\n      '31': 0\n    },\n    f: {\n      '0': 0,\n      '1': 0,\n      '2': 0,\n      '3': 0,\n      '4': 0,\n      '5': 0,\n      '6': 0,\n      '7': 0,\n      '8': 0,\n      '9': 0,\n      '10': 0,\n      '11': 0,\n      '12': 0,\n      '13': 0,\n      '14': 0,\n      '15': 0,\n      '16': 0,\n      '17': 0,\n      '18': 0,\n      '19': 0\n    },\n    b: {},\n    _coverageSchema: '332fd63041d2c1bcb487cc26dd0d5f7d97098a6c'\n  },\n      coverage = global[gcv] || (global[gcv] = {});\n\n  if (coverage[path] && coverage[path].hash === hash) {\n    return coverage[path];\n  }\n\n  coverageData.hash = hash;\n  return coverage[path] = coverageData;\n}();\n\nvar _Utils = require('./Utils');\n\nvar utils = _interopRequireWildcard(_Utils);\n\nvar _httpUtil = require('./httpUtil');\n\nvar HTTP = _interopRequireWildcard(_httpUtil);\n\nfunction _interopRequireWildcard(obj) { if (obj && obj.__esModule) { return obj; } else { var newObj = {}; if (obj != null) { for (var key in obj) { if (Object.prototype.hasOwnProperty.call(obj, key)) newObj[key] = obj[key]; } } newObj.default = obj; return newObj; } }\n\nvar apiDomain = (cov_ov9eokzlk.s[0]++, require('./ApiConst').apiWayBillDomain);\n\nfunction list(paramObj, cb) {\n  cov_ov9eokzlk.f[0]++;\n\n  var apiUrl = (cov_ov9eokzlk.s[1]++, apiDomain + '/waybill_ticket_detail/list');\n  cov_ov9eokzlk.s[2]++;\n  HTTP.get(apiUrl, paramObj, function (response, error) {\n    cov_ov9eokzlk.f[1]++;\n    cov_ov9eokzlk.s[3]++;\n\n    cb(response, error);\n  });\n}\n\nfunction getColumn(cb) {\n  cov_ov9eokzlk.f[2]++;\n\n  var apiUrl = (cov_ov9eokzlk.s[4]++, apiDomain + '/list_render_info/ticket/list');\n  cov_ov9eokzlk.s[5]++;\n  HTTP.get(apiUrl, {}, function (res, error) {\n    cov_ov9eokzlk.f[3]++;\n    cov_ov9eokzlk.s[6]++;\n\n    cb(res, error);\n  });\n}\n\nfunction getSearch(cb) {\n  cov_ov9eokzlk.f[4]++;\n\n  var apiUrl = (cov_ov9eokzlk.s[7]++, apiDomain + '/search_render_info/ticket/list');\n  cov_ov9eokzlk.s[8]++;\n  HTTP.get(apiUrl, {}, function (res, error) {\n    cov_ov9eokzlk.f[5]++;\n    cov_ov9eokzlk.s[9]++;\n\n    cb(res, error);\n  });\n}\n\nfunction deleted(paramObj, cb) {\n  cov_ov9eokzlk.f[6]++;\n\n  var apiUrl = (cov_ov9eokzlk.s[10]++, apiDomain + '/waybill_ticket_detail/' + paramObj.code + '/delete');\n  cov_ov9eokzlk.s[11]++;\n  HTTP.post(apiUrl, paramObj, function (res) {\n    cov_ov9eokzlk.f[7]++;\n    cov_ov9eokzlk.s[12]++;\n\n    cb(res);\n  });\n}\n\nfunction add(paramObj, cb) {\n  cov_ov9eokzlk.f[8]++;\n\n  var apiUrl = (cov_ov9eokzlk.s[13]++, apiDomain + '/waybill_ticket_detail/add');\n  cov_ov9eokzlk.s[14]++;\n  HTTP.post(apiUrl, paramObj, function (res, error) {\n    cov_ov9eokzlk.f[9]++;\n    cov_ov9eokzlk.s[15]++;\n\n    cb(res, error);\n  });\n}\n\nfunction edit(code, paramObj, cb) {\n  cov_ov9eokzlk.f[10]++;\n\n  var apiUrl = (cov_ov9eokzlk.s[16]++, apiDomain + '/waybill_ticket_detail/' + code + '/edit');\n  cov_ov9eokzlk.s[17]++;\n  HTTP.post(apiUrl, paramObj, function (res, error) {\n    cov_ov9eokzlk.f[11]++;\n    cov_ov9eokzlk.s[18]++;\n\n    cb(res, error);\n  });\n}\n\nfunction get(paramObj, cb) {\n  cov_ov9eokzlk.f[12]++;\n\n  var apiUrl = (cov_ov9eokzlk.s[19]++, apiDomain + '/waybill_ticket_detail/' + paramObj.code + '/get');\n  cov_ov9eokzlk.s[20]++;\n  delete paramObj.code;\n  cov_ov9eokzlk.s[21]++;\n  HTTP.get(apiUrl, paramObj, function (res, error) {\n    cov_ov9eokzlk.f[13]++;\n    cov_ov9eokzlk.s[22]++;\n\n    cb(res, error);\n  });\n}\n\nfunction exportCsv(paramObj, callback) {\n  cov_ov9eokzlk.f[14]++;\n\n  var apiUrl = (cov_ov9eokzlk.s[23]++, apiDomain + '/export/ticket');\n  cov_ov9eokzlk.s[24]++;\n  HTTP.get(apiUrl, paramObj, function (success, error) {\n    cov_ov9eokzlk.f[15]++;\n    cov_ov9eokzlk.s[25]++;\n\n    callback(success, error);\n  });\n}\n\nfunction downloadErrorData(paramObj, callback) {\n  cov_ov9eokzlk.f[16]++;\n\n  var apiUrl = (cov_ov9eokzlk.s[26]++, apiDomain + '/generator/ticket');\n  cov_ov9eokzlk.s[27]++;\n  HTTP.post(apiUrl, paramObj, function (success, error) {\n    cov_ov9eokzlk.f[17]++;\n    cov_ov9eokzlk.s[28]++;\n\n    callback(success, error);\n  });\n}\n\nfunction downloadTemplate(paramObj, callback) {\n  cov_ov9eokzlk.f[18]++;\n\n  var apiUrl = (cov_ov9eokzlk.s[29]++, apiDomain + '/download/template/ticket');\n  cov_ov9eokzlk.s[30]++;\n  HTTP.get(apiUrl, paramObj, function (success, error) {\n    cov_ov9eokzlk.f[19]++;\n    cov_ov9eokzlk.s[31]++;\n\n    callback(success, error);\n  });\n}\n\nexports.list = list;\nexports.getColumn = getColumn;\nexports.getSearch = getSearch;\nexports.deleted = deleted;\nexports.add = add;\nexports.edit = edit;\nexports.get = get;\nexports.exportCsv = exportCsv;\nexports.downloadErrorData = downloadErrorData;\nexports.downloadTemplate = downloadTemplate;",{"version":3,"sources":["api/ticketDetailService.js"],"names":["utils","HTTP","apiDomain","require","apiWayBillDomain","list","paramObj","cb","apiUrl","get","response","error","getColumn","res","getSearch","deleted","code","post","add","edit","exportCsv","callback","success","downloadErrorData","downloadTemplate"],"mappings":";;;;;;;;;;;;;;;;;;;;;;;;;;;;;;;;;;;;;;;;;;;;;;;;;;;;;;;;;;;;;;;;;;;;;;;;;;;;;;;;;;;;;;;;;;;;;;;;;;;;;;;;;;;;;;;;;;;;;;;;;;;;;;;;;;;;;;;;;;;;;;;;;;;;;;;;;;;;;;;;;;;;;;;;;;;;;;;;;;;;;;;;;;;;;;;;;;;;;;;;;;;;;;;;;;;;;;;;;;;;;;;;;;;;;;;;;;;;;;;;;;;;;;;;;;;;;;;;;;;;;;;;;;;;;;;;;;;;;;;;;;;;;;;;;;;;;;;;;;;;;;;;;;;;;;;;;;;;;;;;;;;;;;;;;;;;;;;;;;;;;;;;;;;;;;;;;;;;;;;;;;;;;;;;;;;;;;;;;;;;;;;;;;;;;;;;;;;;;;;;;;;;;;;;;;;;;;;;;;;;;;;;;;;;;;;;;;;;;;;;;;;;;;;;;;;;;;;;;;;;;;;;;;;;;;;;;;;;;;;;;;;;;;;;;;;;;;;;;;;;;;;;;;;;;;;;;;;;;;;;;;;;;;;;;;;;;;;;;;;;;;;;;;;;;;;;;;;;;;;;;;;;;;;;;;;;;;;;;;;;;;;;;;;;;;;;;;;;;;;;;;;;;;;;;;;;;;;;;;;;;;;;;;;;;;;;;;;;;;;;;;;;;;;;;;;;;;;;;;;;;;;;;;;;;;;;;;;;;;;;;;;;;;;;;;;;;;;;;;;;;;;;;;;;;;;;;;;;;;;;;;;;;;;;;;;;;;;;;;;;;;;;;;;;;;;;;;;;;;;;;;;;;;;;;;;;;;;;;;;;;;;;;;;;;;;;;;;;;;;;;;;;;;;;;;;;;;;;;;;;;;;;;;;;;;;;;;;;;;;;;;;;;;;;;;;;;;;;;;;;;;;;;;;;;;;;;;;;;;;;;;;;;;;;AAIA;;IAAYA,K;;AAIZ;;IAAYC,I;;;;AAFZ,IAAMC,mCAAYC,QAAQ,YAAR,EAAsBC,gBAAlC,CAAN;;AAYA,SAASC,IAAT,CAAcC,QAAd,EAAwBC,EAAxB,EAA4B;AAAA;;AAC1B,MAAMC,gCAAYN,SAAZ,iCAAN;AAD0B;AAE1BD,OAAKQ,GAAL,CAASD,MAAT,EAAiBF,QAAjB,EAA2B,UAACI,QAAD,EAAWC,KAAX,EAAqB;AAAA;AAAA;;AAC9CJ,OAAGG,QAAH,EAAaC,KAAb;AACD,GAFD;AAGD;;AAMD,SAASC,SAAT,CAAmBL,EAAnB,EAAuB;AAAA;;AACrB,MAAMC,gCAAYN,SAAZ,mCAAN;AADqB;AAErBD,OAAKQ,GAAL,CAASD,MAAT,EAAiB,EAAjB,EAAqB,UAACK,GAAD,EAAMF,KAAN,EAAgB;AAAA;AAAA;;AACnCJ,OAAGM,GAAH,EAAQF,KAAR;AACD,GAFD;AAGD;;AAMD,SAASG,SAAT,CAAmBP,EAAnB,EAAuB;AAAA;;AACrB,MAAMC,gCAAYN,SAAZ,qCAAN;AADqB;AAErBD,OAAKQ,GAAL,CAASD,MAAT,EAAiB,EAAjB,EAAqB,UAACK,GAAD,EAAMF,KAAN,EAAgB;AAAA;AAAA;;AACnCJ,OAAGM,GAAH,EAAQF,KAAR;AACD,GAFD;AAGD;;AAQD,SAASI,OAAT,CAAiBT,QAAjB,EAA2BC,EAA3B,EAA+B;AAAA;;AAC7B,MAAMC,iCAAYN,SAAZ,+BAA+CI,SAASU,IAAxD,aAAN;AAD6B;AAE7Bf,OAAKgB,IAAL,CAAUT,MAAV,EAAkBF,QAAlB,EAA4B,UAACO,GAAD,EAAS;AAAA;AAAA;;AACnCN,OAAGM,GAAH;AACD,GAFD;AAGD;;AAOD,SAASK,GAAT,CAAaZ,QAAb,EAAuBC,EAAvB,EAA2B;AAAA;;AACzB,MAAMC,iCAAYN,SAAZ,gCAAN;AADyB;AAEzBD,OAAKgB,IAAL,CAAUT,MAAV,EAAkBF,QAAlB,EAA4B,UAACO,GAAD,EAAMF,KAAN,EAAgB;AAAA;AAAA;;AAC1CJ,OAAGM,GAAH,EAAQF,KAAR;AACD,GAFD;AAGD;;AAOD,SAASQ,IAAT,CAAcH,IAAd,EAAoBV,QAApB,EAA8BC,EAA9B,EAAkC;AAAA;;AAChC,MAAMC,iCAAYN,SAAZ,+BAA+Cc,IAA/C,WAAN;AADgC;AAEhCf,OAAKgB,IAAL,CAAUT,MAAV,EAAkBF,QAAlB,EAA4B,UAACO,GAAD,EAAMF,KAAN,EAAgB;AAAA;AAAA;;AAC1CJ,OAAGM,GAAH,EAAQF,KAAR;AACD,GAFD;AAGD;;AAQD,SAASF,GAAT,CAAaH,QAAb,EAAuBC,EAAvB,EAA2B;AAAA;;AACzB,MAAMC,iCAAYN,SAAZ,+BAA+CI,SAASU,IAAxD,UAAN;AADyB;AAEzB,SAAOV,SAASU,IAAhB;AAFyB;AAGzBf,OAAKQ,GAAL,CAASD,MAAT,EAAiBF,QAAjB,EAA2B,UAACO,GAAD,EAAMF,KAAN,EAAgB;AAAA;AAAA;;AACzCJ,OAAGM,GAAH,EAAQF,KAAR;AACD,GAFD;AAGD;;AAMD,SAASS,SAAT,CAAmBd,QAAnB,EAA6Be,QAA7B,EAAuC;AAAA;;AACrC,MAAMb,iCAAYN,SAAZ,oBAAN;AADqC;AAErCD,OAAKQ,GAAL,CAASD,MAAT,EAAiBF,QAAjB,EAA2B,UAACgB,OAAD,EAAUX,KAAV,EAAoB;AAAA;AAAA;;AAC7CU,aAASC,OAAT,EAAkBX,KAAlB;AACD,GAFD;AAGD;;AAKD,SAASY,iBAAT,CAA2BjB,QAA3B,EAAqCe,QAArC,EAA+C;AAAA;;AAC7C,MAAMb,iCAAYN,SAAZ,uBAAN;AAD6C;AAE7CD,OAAKgB,IAAL,CAAUT,MAAV,EAAkBF,QAAlB,EAA4B,UAACgB,OAAD,EAAUX,KAAV,EAAoB;AAAA;AAAA;;AAC9CU,aAASC,OAAT,EAAkBX,KAAlB;AACD,GAFD;AAGD;;AAKD,SAASa,gBAAT,CAA0BlB,QAA1B,EAAoCe,QAApC,EAA8C;AAAA;;AAC5C,MAAMb,iCAAYN,SAAZ,+BAAN;AAD4C;AAE5CD,OAAKQ,GAAL,CAASD,MAAT,EAAiBF,QAAjB,EAA2B,UAACgB,OAAD,EAAUX,KAAV,EAAoB;AAAA;AAAA;;AAC7CU,aAASC,OAAT,EAAkBX,KAAlB;AACD,GAFD;AAGD;;QAEQN,I,GAAAA,I;QAAMO,S,GAAAA,S;QAAWE,S,GAAAA,S;QAAWC,O,GAAAA,O;QAASG,G,GAAAA,G;QAAKC,I,GAAAA,I;QAAMV,G,GAAAA,G;QAAKW,S,GAAAA,S;QAAWG,iB,GAAAA,iB;QAAmBC,gB,GAAAA,gB","file":"ticketDetailService.js","sourceRoot":"/Users/macsen/Desktop/Macsen/rltx-webpack","sourcesContent":["/**\n * Created by cc on 2017/6/30.\n */\n\nimport * as utils from './Utils';\n\nconst apiDomain = require('./ApiConst').apiWayBillDomain;\n\nimport * as HTTP from './httpUtil';\n\n/**\n * 获取列表\n * @param routeTag      线路标签\n * @param mark          检索\n * @param page          页码\n * @param size          页长\n * @param callback      回调\n */\nfunction list(paramObj, cb) {\n  const apiUrl = `${apiDomain}/waybill_ticket_detail/list`;\n  HTTP.get(apiUrl, paramObj, (response, error) => {\n    cb(response, error);\n  });\n}\n\n/**\n * 获取table头部数据\n * @param callback\n */\nfunction getColumn(cb) {\n  const apiUrl = `${apiDomain}/list_render_info/ticket/list`;\n  HTTP.get(apiUrl, {}, (res, error) => {\n    cb(res, error);\n  });\n}\n\n/**\n * 获取search数据\n * @param callback\n */\nfunction getSearch(cb) {\n  const apiUrl = `${apiDomain}/search_render_info/ticket/list`;\n  HTTP.get(apiUrl, {}, (res, error) => {\n    cb(res, error);\n  });\n}\n\n/**\n * 删除\n * @param paramObj          参数对象\n *        code              编码\n * @param callback          回调\n */\nfunction deleted(paramObj, cb) {\n  const apiUrl = `${apiDomain}/waybill_ticket_detail/${paramObj.code}/delete`;\n  HTTP.post(apiUrl, paramObj, (res) => {\n    cb(res);\n  });\n}\n\n/**\n * 添加\n * @param partnerName       简称\n * @param callback          回调\n */\nfunction add(paramObj, cb) {\n  const apiUrl = `${apiDomain}/waybill_ticket_detail/add`;\n  HTTP.post(apiUrl, paramObj, (res, error) => {\n    cb(res, error);\n  });\n}\n\n/**\n * 编辑\n * @param partnerName       简称\n * @param callback          回调\n */\nfunction edit(code, paramObj, cb) {\n  const apiUrl = `${apiDomain}/waybill_ticket_detail/${code}/edit`;\n  HTTP.post(apiUrl, paramObj, (res, error) => {\n    cb(res, error);\n  });\n}\n\n/**\n * 根据编码获取详情\n * @param paramObj        参数对象\n *        code\n * @param callback\n */\nfunction get(paramObj, cb) {\n  const apiUrl = `${apiDomain}/waybill_ticket_detail/${paramObj.code}/get`;\n  delete paramObj.code;\n  HTTP.get(apiUrl, paramObj, (res, error) => {\n    cb(res, error);\n  });\n}\n\n/**\n * export\n * @param callback\n */\nfunction exportCsv(paramObj, callback) {\n  const apiUrl = `${apiDomain}/export/ticket`;\n  HTTP.get(apiUrl, paramObj, (success, error) => {\n    callback(success, error);\n  });\n}\n\n/**\n * 下载错误数据的CSV文件\n */\nfunction downloadErrorData(paramObj, callback) {\n  const apiUrl = `${apiDomain}/generator/ticket`;\n  HTTP.post(apiUrl, paramObj, (success, error) => {\n    callback(success, error);\n  });\n}\n\n/**\n * 下载CSV模板\n */\nfunction downloadTemplate(paramObj, callback) {\n  const apiUrl = `${apiDomain}/download/template/ticket`;\n  HTTP.get(apiUrl, paramObj, (success, error) => {\n    callback(success, error);\n  });\n}\n\nexport { list, getColumn, getSearch, deleted, add, edit, get, exportCsv, downloadErrorData, downloadTemplate };\n"]}]}