{"remainingRequest":"/Users/macsen/Desktop/rltx-webpack/src/safe/safe.js","dependencies":[{"path":"/Users/macsen/Desktop/rltx-webpack/src/safe/safe.js","mtime":1511527697000},{"path":"/Users/macsen/Desktop/rltx-webpack/node_modules/_babel-loader@6.2.10@babel-loader/lib/index.js","mtime":1481808750000},{"path":"/Users/macsen/Desktop/rltx-webpack/node_modules/_cache-loader@1.2.0@cache-loader/dist/cjs.js","mtime":1510929699000}],"contextDependencies":[],"result":["import { Message, Form, FormItem, button, Input } from 'element-ui';\r\nimport Vue from 'vue';\r\nimport safe from './safe.vue';\r\nimport { removeClass } from '../../api/classUtil';\r\n\r\nVue.prototype.$message = Message;\r\nVue.use(Form);\r\nVue.use(FormItem);\r\nVue.use(button);\r\nVue.use(Input);\r\n\r\nrequire('../public.js');\r\n\r\n/* eslint-disable no-new */\r\n/* eslint-disable no-unused-vars */\r\nconst vm = new Vue({\r\n  el: '#app',\r\n  data: {\r\n    type: 1\r\n  },\r\n  template: '<safe :type=\"type\"/>',\r\n  components: { safe }\r\n});\r\n\r\nfunction showDialog() {\r\n  const masklayer = document.getElementById('maskLayer'),\r\n    dialog = document.getElementById('dialog');\r\n  removeClass(masklayer, 'hide');\r\n  removeClass(dialog, 'hide');\r\n}\r\n\r\nfunction showDialog1() {\r\n  const masklayer = document.getElementById('maskLayer'),\r\n    dialog = document.getElementById('dialog1');\r\n  removeClass(masklayer, 'hide');\r\n  removeClass(dialog, 'hide');\r\n}\r\n\r\ndocument.getElementById('pwd_update').onclick = function () {\r\n  showDialog();\r\n};\r\n\r\ndocument.getElementById('phone_update').onclick = function () {\r\n  showDialog1();\r\n};\r\n",null]}